redis_retrieval_optimizer/__init__.py
redis_retrieval_optimizer/bayes_study.py
redis_retrieval_optimizer/corpus_processors/__init__.py
redis_retrieval_optimizer/corpus_processors/eval_beir.py
redis_retrieval_optimizer/grid_study.py
redis_retrieval_optimizer/schema.py
redis_retrieval_optimizer/search_methods/__init__.py
redis_retrieval_optimizer/search_methods/base.py
redis_retrieval_optimizer/search_methods/bm25.py
redis_retrieval_optimizer/search_methods/hybrid.py
redis_retrieval_optimizer/search_methods/hybrid_8_4.py
redis_retrieval_optimizer/search_methods/rerank.py
redis_retrieval_optimizer/search_methods/rrf_8_4.py
redis_retrieval_optimizer/search_methods/vector.py
redis_retrieval_optimizer/search_methods/weighted_rrf.py
redis_retrieval_optimizer/search_study.py
redis_retrieval_optimizer/threshold_optimization/__init__.py
redis_retrieval_optimizer/threshold_optimization/base.py
redis_retrieval_optimizer/threshold_optimization/cache.py
redis_retrieval_optimizer/threshold_optimization/router.py
redis_retrieval_optimizer/threshold_optimization/schema.py
redis_retrieval_optimizer/threshold_optimization/utils.py
redis_retrieval_optimizer/utils.py
redis_retrieval_optimizer-0.5.0.dist-info/WHEEL
redis_retrieval_optimizer-0.5.0.dist-info/entry_points.txt
redis_retrieval_optimizer-0.5.0.dist-info/METADATA
redis_retrieval_optimizer-0.5.0.dist-info/RECORD
