Metadata-Version: 2.3
Name: redis-retrieval-optimizer
Version: 0.5.0
Summary: A tool to help optimize information retrieval with the Redis Query Engine.
Author: Robert Shelton
Author-email: Robert Shelton <robert.shelton@redis.com>
License: MIT
Requires-Dist: redisvl>=0.13.0
Requires-Dist: optuna>=4.3.0,<5.0.0
Requires-Dist: numpy>=1.26,<3.0.0
Requires-Dist: pandas>=2.0,<3.0.0
Requires-Dist: redis>=7.1.0
Requires-Dist: ranx>=0.3.20,<0.4.0
Requires-Dist: beir>=2.1.0,<3.0.0
Requires-Dist: python-dotenv>=1.1.0,<2.0.0
Requires-Dist: nltk>=3.9.1,<4.0.0
Requires-Dist: ulid>=1.1
Requires-Python: >=3.11, <3.14
